wagtail_plotly/__init__.py
wagtail_plotly/apps.py
wagtail_plotly/config.py
wagtail_plotly/models.py
wagtail_plotly/utils.py
wagtail_plotly/blocks/__init__.py
wagtail_plotly/blocks/base.py
wagtail_plotly/blocks/blocks.py
wagtail_plotly/blocks/table.py
wagtail_plotly/static/wagtail_plotly/css/plot_data_table.css
wagtail_plotly/static/wagtail_plotly/js/plot_data_table.js
wagtail_plotly/templates/wagtail_plotly/blocks/plot.html
wagtail_plotly-0.0.4.dist-info/LICENSE
wagtail_plotly-0.0.4.dist-info/METADATA
wagtail_plotly-0.0.4.dist-info/WHEEL
wagtail_plotly-0.0.4.dist-info/top_level.txt
wagtail_plotly-0.0.4.dist-info/RECORD
