Metadata-Version: 2.1
Name: wagtail_plotly
Version: 0.0.4
Summary: Plotly for Wagtail CMS
Home-page: https://github.com/cursive-works/wagtail-plotly
Author: Martin Swarbrick
Author-email: martin.swarbrick@cursive.works
License: MIT
Keywords: WAGTAIL,PLOTLY,STREAMFIELD,WAGTAIL_PLOTLY,WAGTAIL CMS
Classifier: Development Status :: 4 - Beta
Classifier: Environment :: Web Environment
Classifier: Framework :: Django
Classifier: Intended Audience :: Developers
Classifier: License :: OSI Approved :: MIT License
Classifier: Operating System :: OS Independent
Classifier: Programming Language :: Python
Classifier: Programming Language :: Python :: 3.7
Classifier: Programming Language :: Python :: 3.8
Classifier: Programming Language :: Python :: 3.9
Classifier: Topic :: Internet :: WWW/HTTP
Classifier: Topic :: Internet :: WWW/HTTP :: Dynamic Content
Classifier: Topic :: Software Development
License-File: LICENSE
Requires-Dist: plotly>=4.14.3
Requires-Dist: wagtail>=3.0
Requires-Dist: wagtail-json-widget>=0.0.1
